{
    "id": "Kafka",
    "type": "chart",
    "node_affinity": "Sensor",
    "formControls": [
        {
          "type": "textinput",
          "default_value": "24",
          "description": "Enter how long to retain messages in hours",
          "required": true,
          "regexp": "^\\d+$",
          "name": "log_retention_hours",
          "error_message": "Enter valid number"
        },
        {
          "type": "invisible",
          "name": "affinity_hostname"
        },
        {
          "type": "invisible",
          "name": "node_hostname"
        }
    ]
}
